{"id":"ol-OL8455255W-tokyo","bookTitle":"City of Bones","author":"Cassandra Clare","publishYear":2007,"placeName":"Tokyo","coordinates":[139.6917,35.6895],"placeType":"real","settingType":"primary","narrativeEra":"2007s","passage":"Clary Fray is seeing things : Vampires in Brooklyn and werewolves in Manhattan. Irresistibly drawn by a group of sexy \r\ndemon hunters, Clary encounters the dark side of new york city - and the dangers of forbidden love.","sentiment":{"polarity":0.2,"dominantEmotions":["intoxication","restlessness","electricity","mischief"],"themes":["hidden_urban_supernatural_layers","transgressive_youth_romance","dichotomy_of_neon_and_shadow","adolescent_identity_crisis","modern_gothic_aestheticism"]},"language":"Spanish","genres":["children's","fantasy","horror","literary fiction","magical realism","romance","young adult"],"region":"East Asia","openLibraryKey":"/works/OL8455255W","coverUrl":"https://covers.openlibrary.org/b/id/10121449-M.jpg","source":"openlibrary","openLibraryUrl":"https://openlibrary.org/works/OL8455255W","literaryMood":"urban_fantasy_kinetic","placeGranularity":"city","coordinatePrecisionKm":15,"coordinateConfidence":0.85,"coordinateSource":"openlibrary","geolocationNeedsReview":false,"passageSource":"openlibrary","passageType":"ol_description","enrichmentMethod":"gemini_passage","qualityTier":"gold","geoQuality":1.0,"geoRiskFlags":[],"qualityScore":1.0,"qualityPassed":true,"@context":"https://schema.org","@type":"Book","spatialCoverage":{"@type":"Place","name":"Tokyo","geo":{"@type":"GeoCoordinates","longitude":139.6917,"latitude":35.6895}},"contentLocation":{"@type":"Place","name":"Tokyo","geo":{"@type":"GeoCoordinates","longitude":139.6917,"latitude":35.6895}},"sameAs":["https://openlibrary.org/works/OL8455255W"]}