{"id":"ol-OL4788564W-jaipur","bookTitle":"Jaipur nama","author":"G. H. R. Tillotson","publishYear":2006,"placeName":"Jaipur","coordinates":[75.7873,26.9124],"placeType":"real","settingType":"primary","narrativeEra":"2006s","passage":"","sentiment":{"polarity":0.6,"dominantEmotions":["reverence","wistfulness","serenity","pride"],"themes":["architectural_legacy","rajput_court_history","urban_planning_ideals","colonial_encounter","preservation_of_heritage","aesthetic_continuity"]},"language":"English","genres":["literary fiction"],"region":"South Asia","openLibraryKey":"/works/OL4788564W","coverUrl":"https://covers.openlibrary.org/b/id/13524681-M.jpg","source":"openlibrary","openLibraryUrl":"https://openlibrary.org/works/OL4788564W","literaryMood":"contemplative","placeGranularity":"city","coordinatePrecisionKm":15,"coordinateConfidence":0.85,"coordinateSource":"openlibrary","geolocationNeedsReview":false,"passageSource":"openlibrary","passageType":"none","enrichmentMethod":"gemini_reputation","qualityTier":"silver","geoQuality":1.0,"geoRiskFlags":[],"qualityScore":0.825,"qualityPassed":true,"@context":"https://schema.org","@type":"Book","spatialCoverage":{"@type":"Place","name":"Jaipur","geo":{"@type":"GeoCoordinates","longitude":75.7873,"latitude":26.9124}},"contentLocation":{"@type":"Place","name":"Jaipur","geo":{"@type":"GeoCoordinates","longitude":75.7873,"latitude":26.9124}},"sameAs":["https://openlibrary.org/works/OL4788564W"]}