{"id":"ol-OL3741419W-tokyo","bookTitle":"Coin Locker Babies","author":"Ryū Murakami","publishYear":1995,"placeName":"Tokyo","coordinates":[139.6917,35.6895],"placeType":"real","settingType":"primary","narrativeEra":"1995s","passage":"","sentiment":{"polarity":-0.8,"dominantEmotions":["revulsion","fury","fever","claustrophobia","obsession"],"themes":["infant_abandonment","urban_nihilism","maternal_rejection","chemical_warfare","media_saturation","visceral_transgression"]},"language":"English","genres":["literary fiction","social realism"],"region":"East Asia","openLibraryKey":"/works/OL3741419W","coverUrl":"https://covers.openlibrary.org/b/id/1043464-M.jpg","source":"openlibrary","literaryMood":"hallucinatory","placeGranularity":"city","coordinatePrecisionKm":15,"coordinateConfidence":0.85,"coordinateSource":"openlibrary","geolocationNeedsReview":false,"passageSource":"openlibrary","passageType":"none","enrichmentMethod":"gemini_reputation","qualityTier":"silver","geoQuality":1.0,"geoRiskFlags":[],"qualityScore":0.825,"qualityPassed":true,"@context":"https://schema.org","@type":"Book","spatialCoverage":{"@type":"Place","name":"Tokyo","geo":{"@type":"GeoCoordinates","longitude":139.6917,"latitude":35.6895}},"contentLocation":{"@type":"Place","name":"Tokyo","geo":{"@type":"GeoCoordinates","longitude":139.6917,"latitude":35.6895}},"sameAs":["https://openlibrary.org/works/OL3741419W"]}