{"id":"ol-OL20150260W-dublin","bookTitle":"Normal People","author":"Sally Rooney","publishYear":2018,"placeName":"Dublin","coordinates":[-6.2603,53.3498],"placeType":"real","settingType":"primary","narrativeEra":"2018s","passage":"At school Connell and Marianne pretend not to know each other. He’s popular and well-adjusted, star of the school soccer team while she is lonely, proud, and intensely private. But when Connell comes to pick his mother up from her housekeeping job at Marianne’s house, a strange and indelible connection grows between the two teenagers - one they are determined to conceal.\r\n\r\nA year later, they’re b...","sentiment":{"polarity":0.2,"dominantEmotions":["claustrophobia","restlessness","wistfulness","tenderness","shame"],"themes":["class_disparity","academic_elitism","social_performance","power_imbalance","transient_intimacy","post_recession_precarity"]},"language":"English","genres":["literary fiction","romance","social realism"],"region":"Europe","openLibraryKey":"/works/OL20150260W","coverUrl":"https://covers.openlibrary.org/b/id/8794265-M.jpg","source":"openlibrary","openLibraryUrl":"https://openlibrary.org/works/OL20150260W","literaryMood":"introspective","placeGranularity":"city","coordinatePrecisionKm":15,"coordinateConfidence":0.85,"coordinateSource":"openlibrary","geolocationNeedsReview":false,"passageSource":"openlibrary","passageType":"ol_description","enrichmentMethod":"gemini_passage","qualityTier":"gold","geoQuality":1.0,"geoRiskFlags":[],"qualityScore":1.0,"qualityPassed":true,"@context":"https://schema.org","@type":"Book","spatialCoverage":{"@type":"Place","name":"Dublin","geo":{"@type":"GeoCoordinates","longitude":-6.2603,"latitude":53.3498}},"contentLocation":{"@type":"Place","name":"Dublin","geo":{"@type":"GeoCoordinates","longitude":-6.2603,"latitude":53.3498}},"sameAs":["https://openlibrary.org/works/OL20150260W"]}