{"id":"ol-OL16152273W-bangalore","bookTitle":"These Foolish Things","author":"Deborah Moggach","publishYear":2004,"placeName":"Bangalore","coordinates":[77.5946,12.9716],"placeType":"real","settingType":"primary","narrativeEra":"2004s","passage":"Enticed by advertisements for a newly restored palatial hotel and filled with visions of a life of leisure, good weather and mango juice in their gin, a group of very different people leave England to begin a new life in India. On arrival they are dismayed to find the palace is a shell of its former self, the staff more than a little eccentric, and the days of the Raj long gone. But, as they soon ...","sentiment":{"polarity":0.2,"dominantEmotions":["wistfulness","mischief","languor","ambivalence"],"themes":["outsourcing_of_retirement","postcolonial_disillusionment","cultural_displacement","intergenerational_clash","aging_in_a_foreign_landscape"]},"language":"English","genres":["literary fiction"],"region":"South Asia","openLibraryKey":"/works/OL16152273W","coverUrl":"https://covers.openlibrary.org/b/id/447578-M.jpg","source":"openlibrary","openLibraryUrl":"https://openlibrary.org/works/OL16152273W","literaryMood":"whimsical","placeGranularity":"city","coordinatePrecisionKm":15,"coordinateConfidence":0.85,"coordinateSource":"openlibrary","geolocationNeedsReview":false,"passageSource":"openlibrary","passageType":"ol_description","enrichmentMethod":"gemini_passage","qualityTier":"gold","geoQuality":1.0,"geoRiskFlags":[],"qualityScore":1.0,"qualityPassed":true,"@context":"https://schema.org","@type":"Book","spatialCoverage":{"@type":"Place","name":"Bangalore","geo":{"@type":"GeoCoordinates","longitude":77.5946,"latitude":12.9716}},"contentLocation":{"@type":"Place","name":"Bangalore","geo":{"@type":"GeoCoordinates","longitude":77.5946,"latitude":12.9716}},"sameAs":["https://openlibrary.org/works/OL16152273W"]}