{"id":"ol-OL353355W-gorakhpur","bookTitle":"Śrīrādhā-Mādhava-cintana","author":"Hanuman Prasad Poddar","publishYear":1964,"placeName":"Gorakhpur","coordinates":[83.3732,26.7606],"placeType":"real","settingType":"primary","narrativeEra":"1964s","passage":"Lord Krishna is the Hindu deity ,incarnation of God and Shri Radha was his beloved. The love for Shri Radha for lord Krishna was not sensual(passionate) and it was highest subtle love ever possible between two human beings. The name of Shri Radha is always enchanted before Shri Krishna .According to Hindu mythology , the mercy of Lord Krishna can not be obtained without worshipping Shri Radha . In...","sentiment":{"polarity":0.9,"dominantEmotions":["reverence","serenity","gratitude","tenderness"],"themes":["divine_devotion","bhakti_tradition","spiritual_surrender","sacred_geography","metaphysical_union"]},"language":"Hindi","genres":["literary fiction"],"region":"South Asia","openLibraryKey":"/works/OL353355W","coverUrl":"https://covers.openlibrary.org/b/id/6676868-M.jpg","source":"openlibrary","openLibraryUrl":"https://openlibrary.org/works/OL353355W","literaryMood":"devotional","placeGranularity":"city","coordinatePrecisionKm":15,"coordinateConfidence":0.85,"coordinateSource":"openlibrary","geolocationNeedsReview":false,"passageSource":"openlibrary","passageType":"ol_description","enrichmentMethod":"gemini_passage","qualityTier":"gold","geoQuality":1.0,"geoRiskFlags":[],"qualityScore":1.0,"qualityPassed":true,"@context":"https://schema.org","@type":"Book","spatialCoverage":{"@type":"Place","name":"Gorakhpur","geo":{"@type":"GeoCoordinates","longitude":83.3732,"latitude":26.7606}},"contentLocation":{"@type":"Place","name":"Gorakhpur","geo":{"@type":"GeoCoordinates","longitude":83.3732,"latitude":26.7606}},"sameAs":["https://openlibrary.org/works/OL353355W"]}