{"id":"ol-OL9083110W-pune","bookTitle":"Boots, belts, berets","author":"Tanushree Podder","publishYear":2008,"placeName":"Pune","coordinates":[73.8567,18.5204],"placeType":"real","settingType":"primary","narrativeEra":"2008s","passage":"This book is basically about, a young child how joins (NDA) \"National Defense Academy\" and makes there friends over there and faces so much of challenges and also by concurring them and pass out from the academy","sentiment":{"polarity":0.6,"dominantEmotions":["pride","mischief","solidarity","hope"],"themes":["military_camaraderie","institutional_discipline","adolescent_rites_of_passage","the_nda_microcosm","physical_endurance","heroic_aspiration"]},"language":"English","genres":["literary fiction"],"region":"South Asia","openLibraryKey":"/works/OL9083110W","coverUrl":null,"source":"openlibrary","openLibraryUrl":"https://openlibrary.org/works/OL9083110W","literaryMood":"inspirational","placeGranularity":"city","coordinatePrecisionKm":15,"coordinateConfidence":0.85,"coordinateSource":"openlibrary","geolocationNeedsReview":false,"passageSource":"openlibrary","passageType":"ol_description","enrichmentMethod":"gemini_passage","qualityTier":"gold","geoQuality":1.0,"geoRiskFlags":[],"qualityScore":1.0,"qualityPassed":true,"@context":"https://schema.org","@type":"Book","spatialCoverage":{"@type":"Place","name":"Pune","geo":{"@type":"GeoCoordinates","longitude":73.8567,"latitude":18.5204}},"contentLocation":{"@type":"Place","name":"Pune","geo":{"@type":"GeoCoordinates","longitude":73.8567,"latitude":18.5204}},"sameAs":["https://openlibrary.org/works/OL9083110W"]}