{"id":"ol-OL468431W-new-york","bookTitle":"The Great Gatsby","author":"F. Scott Fitzgerald","publishYear":1920,"placeName":"New York","coordinates":[-74.006,40.7128],"placeType":"real","settingType":"primary","narrativeEra":"1920s","passage":"Here is a novel, glamorous, ironical, compassionate – a marvelous fusion into unity of the curious incongruities of the life of the period – which reveals a hero like no other – one who could live at no other time and in no other place. But he will live as a character, we surmise, as long as the memory of any reader lasts.\r\n\r\n\"There was something gorgeous about him, some heightened sensitivity to ...","sentiment":{"polarity":0.2,"dominantEmotions":["intoxication","wistfulness","obsession","vertigo"],"themes":["excessive_consumption","class_stratification","the_myth_of_the_american_dream","geographical_displacement","performative_wealth","moral_decay"]},"language":"French","genres":["fantasy","literary fiction","romance","social realism","young adult"],"region":"North America","openLibraryKey":"/works/OL468431W","coverUrl":"https://covers.openlibrary.org/b/id/10590366-M.jpg","source":"openlibrary","openLibraryUrl":"https://openlibrary.org/works/OL468431W","literaryMood":"decadent","placeGranularity":"city","coordinatePrecisionKm":15,"coordinateConfidence":0.85,"coordinateSource":"openlibrary","geolocationNeedsReview":false,"passageSource":"openlibrary","passageType":"ol_description","enrichmentMethod":"gemini_passage","qualityTier":"gold","geoQuality":1.0,"geoRiskFlags":[],"qualityScore":1.0,"qualityPassed":true,"@context":"https://schema.org","@type":"Book","spatialCoverage":{"@type":"Place","name":"New York","geo":{"@type":"GeoCoordinates","longitude":-74.006,"latitude":40.7128}},"contentLocation":{"@type":"Place","name":"New York","geo":{"@type":"GeoCoordinates","longitude":-74.006,"latitude":40.7128}},"sameAs":["https://openlibrary.org/works/OL468431W"]}