{"id":"wd-Q1987928-Q8810","bookTitle":"Doña Rosita the Spinster","author":"Federico García Lorca","publishYear":1935,"placeName":"Granada","coordinates":[-3.6,37.175],"placeType":"real","settingType":"primary","narrativeEra":"1935s","passage":"","sentiment":{"polarity":0.0,"dominantEmotions":[],"themes":[]},"language":"Spanish","genres":[],"region":"Europe","country":"Spain","source":"wikidata","openLibraryKey":null,"wikidataBookQid":"Q1987928","wikidataPlaceQid":"Q8810","qaFlags":[],"nearestKnownCity":"Madrid","nearestKnownCityDistanceKm":360.58,"regionInferred":false,"placeGranularity":"city","coordinatePrecisionKm":15,"coordinateConfidence":0.85,"coordinateSource":"wikidata","geolocationNeedsReview":false,"passageSource":"wikidata","passageType":"none","enrichmentMethod":"none","qualityTier":"silver","geoQuality":0.85,"geoRiskFlags":["coarse_coordinate_precision"],"qualityScore":0.78,"qualityPassed":true,"@context":"https://schema.org","@type":"Book","spatialCoverage":{"@type":"Place","name":"Granada","geo":{"@type":"GeoCoordinates","longitude":-3.6,"latitude":37.175}},"contentLocation":{"@type":"Place","name":"Granada","geo":{"@type":"GeoCoordinates","longitude":-3.6,"latitude":37.175}}}