{"id":"wd-Q65557816-Q279373","bookTitle":"Casa di guerra","author":"Isabella Bossi Fedrigotti","publishYear":1983,"placeName":"Rovereto","coordinates":[11.034166666,45.883333333],"placeType":"real","settingType":"primary","narrativeEra":"1983s","passage":"","sentiment":{"polarity":0.0,"dominantEmotions":[],"themes":[]},"language":"Italian","genres":[],"region":"Europe","country":"Italy","source":"wikidata","openLibraryKey":null,"wikidataBookQid":"Q65557816","wikidataPlaceQid":"Q279373","qaFlags":[],"nearestKnownCity":"Rome","nearestKnownCityDistanceKm":457.84,"regionInferred":false,"placeGranularity":"city","coordinatePrecisionKm":15,"coordinateConfidence":0.85,"coordinateSource":"wikidata","geolocationNeedsReview":false,"passageSource":"wikidata","passageType":"none","enrichmentMethod":"none","qualityTier":"silver","geoQuality":1.0,"geoRiskFlags":[],"qualityScore":0.825,"qualityPassed":true,"@context":"https://schema.org","@type":"Book","spatialCoverage":{"@type":"Place","name":"Rovereto","geo":{"@type":"GeoCoordinates","longitude":11.034166666,"latitude":45.883333333}},"contentLocation":{"@type":"Place","name":"Rovereto","geo":{"@type":"GeoCoordinates","longitude":11.034166666,"latitude":45.883333333}}}