{"id":"wd-Q675609-Q2634","bookTitle":"Amok","author":"Stefan Zweig","publishYear":1922,"placeName":"Naples","coordinates":[14.248611111,40.835833333],"placeType":"real","settingType":"primary","narrativeEra":"1922s","passage":"","sentiment":{"polarity":-0.6,"dominantEmotions":["obsession","fever","shame"],"themes":["colonial_doctor_madness","tropical_moral_collapse","zweig_psychological_crisis"]},"language":"German","genres":[],"region":"Europe","country":"Italy","source":"wikidata","openLibraryKey":null,"wikidataBookQid":"Q675609","wikidataPlaceQid":"Q2634","qaFlags":[],"nearestKnownCity":"Rome","nearestKnownCityDistanceKm":188.29,"regionInferred":false,"placeGranularity":"city","coordinatePrecisionKm":15,"coordinateConfidence":0.85,"coordinateSource":"wikidata","geolocationNeedsReview":false,"passageSource":"wikidata","passageType":"none","enrichmentMethod":"gemini_reputation","qualityTier":"silver","geoQuality":1.0,"geoRiskFlags":[],"qualityScore":0.825,"qualityPassed":true,"@context":"https://schema.org","@type":"Book","spatialCoverage":{"@type":"Place","name":"Naples","geo":{"@type":"GeoCoordinates","longitude":14.248611111,"latitude":40.835833333}},"contentLocation":{"@type":"Place","name":"Naples","geo":{"@type":"GeoCoordinates","longitude":14.248611111,"latitude":40.835833333}}}