{"id":"wd-Q302229-Q1017","bookTitle":"St. Cecilia, or the Power of Music","author":"Heinrich von Kleist","publishYear":1810,"placeName":"Aachen","coordinates":[6.083788,50.776207],"placeType":"real","settingType":"primary","narrativeEra":"1810s","passage":"","sentiment":{"polarity":0.0,"dominantEmotions":[],"themes":[]},"language":"German","genres":[],"region":"Europe","country":"Germany","source":"wikidata","openLibraryKey":null,"wikidataBookQid":"Q302229","wikidataPlaceQid":"Q1017","qaFlags":[],"nearestKnownCity":"Amsterdam","nearestKnownCityDistanceKm":194.83,"regionInferred":false,"placeGranularity":"city","coordinatePrecisionKm":15,"coordinateConfidence":0.85,"coordinateSource":"wikidata","geolocationNeedsReview":false,"passageSource":"wikidata","passageType":"none","enrichmentMethod":"none","qualityTier":"silver","geoQuality":1.0,"geoRiskFlags":[],"qualityScore":0.825,"qualityPassed":true,"@context":"https://schema.org","@type":"Book","spatialCoverage":{"@type":"Place","name":"Aachen","geo":{"@type":"GeoCoordinates","longitude":6.083788,"latitude":50.776207}},"contentLocation":{"@type":"Place","name":"Aachen","geo":{"@type":"GeoCoordinates","longitude":6.083788,"latitude":50.776207}}}