{"id":"wd-Q4673026-Q23556","bookTitle":"Ace in the Hole","author":"Walter Jon Williams","publishYear":1990,"placeName":"Atlanta","coordinates":[-84.389722222,33.754444444],"placeType":"real","settingType":"primary","narrativeEra":"1990s","passage":"","sentiment":{"polarity":-0.3,"dominantEmotions":["electricity","mischief","paranoia"],"themes":["superhero_politics","atlanta_convention","wild_cards_universe"]},"language":"English","genres":[],"region":"North America","country":"United States","source":"wikidata","openLibraryKey":null,"wikidataBookQid":"Q4673026","wikidataPlaceQid":"Q23556","qaFlags":["far_from_known_city"],"nearestKnownCity":"Chicago","nearestKnownCityDistanceKm":946.88,"regionInferred":false,"placeGranularity":"city","coordinatePrecisionKm":15,"coordinateConfidence":0.85,"coordinateSource":"wikidata","geolocationNeedsReview":false,"passageSource":"wikidata","passageType":"none","enrichmentMethod":"gemini_reputation","qualityTier":"silver","geoQuality":1.0,"geoRiskFlags":[],"qualityScore":0.825,"qualityPassed":true,"@context":"https://schema.org","@type":"Book","spatialCoverage":{"@type":"Place","name":"Atlanta","geo":{"@type":"GeoCoordinates","longitude":-84.389722222,"latitude":33.754444444}},"contentLocation":{"@type":"Place","name":"Atlanta","geo":{"@type":"GeoCoordinates","longitude":-84.389722222,"latitude":33.754444444}}}