{"id":"wd-Q3570297-Q11208","bookTitle":"X-15","author":"Jean-Michel Charlier","publishYear":1963,"placeName":"The Pentagon","coordinates":[-77.055,38.870833333],"placeType":"real","settingType":"primary","narrativeEra":"1963s","passage":"album de bande dessinée de la série des Aventures de Buck Danny","sentiment":{"polarity":0.4,"dominantEmotions":["pride","electricity","obsession"],"themes":["aerospace_technological_supremacy","cold_war_military_bureaucracy","supersonic_ambition","high_stakes_defense_procurement"]},"language":"Unknown","genres":[],"region":"North America","country":"United States","source":"wikidata","openLibraryKey":null,"wikidataBookQid":"Q3570297","wikidataPlaceQid":"Q11208","qaFlags":[],"nearestKnownCity":"New York","nearestKnownCityDistanceKm":331.34,"regionInferred":false,"literaryMood":"technocratic","placeGranularity":"city","coordinatePrecisionKm":15,"coordinateConfidence":0.85,"coordinateSource":"wikidata","geolocationNeedsReview":false,"passageSource":"wikidata","passageType":"wikidata_stub","enrichmentMethod":"gemini_passage","qualityTier":"silver","geoQuality":1.0,"geoRiskFlags":[],"qualityScore":0.825,"qualityPassed":true,"@context":"https://schema.org","@type":"Book","spatialCoverage":{"@type":"Place","name":"The Pentagon","geo":{"@type":"GeoCoordinates","longitude":-77.055,"latitude":38.870833333}},"contentLocation":{"@type":"Place","name":"The Pentagon","geo":{"@type":"GeoCoordinates","longitude":-77.055,"latitude":38.870833333}}}