{"id":"wd-Q7738761-Q518663","bookTitle":"The Hangman's Daughter","author":"Oliver Pötzsch","publishYear":2008,"placeName":"Q518663","coordinates":[10.9,47.816666666],"placeType":"real","settingType":"primary","narrativeEra":"2008s","passage":"","sentiment":{"polarity":0.0,"dominantEmotions":[],"themes":[]},"language":"German","genres":[],"region":"Europe","country":"Germany","source":"wikidata","openLibraryKey":null,"wikidataBookQid":"Q7738761","wikidataPlaceQid":"Q518663","qaFlags":[],"nearestKnownCity":"Prague","nearestKnownCityDistanceKm":360.25,"regionInferred":false,"placeGranularity":"city","coordinatePrecisionKm":15,"coordinateConfidence":0.85,"coordinateSource":"wikidata","geolocationNeedsReview":false,"passageSource":"wikidata","passageType":"none","enrichmentMethod":"none","qualityTier":"silver","geoQuality":0.85,"geoRiskFlags":["coarse_coordinate_precision"],"qualityScore":0.78,"qualityPassed":true,"@context":"https://schema.org","@type":"Book","spatialCoverage":{"@type":"Place","name":"Q518663","geo":{"@type":"GeoCoordinates","longitude":10.9,"latitude":47.816666666}},"contentLocation":{"@type":"Place","name":"Q518663","geo":{"@type":"GeoCoordinates","longitude":10.9,"latitude":47.816666666}}}