{"id":"wd-Q5985584-Q3447884","bookTitle":"Icebound","author":"Owen Davis","publishYear":1923,"placeName":"Veazie","coordinates":[-68.70531,44.83868],"placeType":"real","settingType":"primary","narrativeEra":"1923s","passage":"","sentiment":{"polarity":0.0,"dominantEmotions":[],"themes":[]},"language":"English","genres":[],"region":"North America","country":"United States","source":"wikidata","openLibraryKey":null,"wikidataBookQid":"Q5985584","wikidataPlaceQid":"Q3447884","qaFlags":[],"nearestKnownCity":"Montreal","nearestKnownCityDistanceKm":388.14,"regionInferred":false,"placeGranularity":"city","coordinatePrecisionKm":15,"coordinateConfidence":0.85,"coordinateSource":"wikidata","geolocationNeedsReview":false,"passageSource":"wikidata","passageType":"none","enrichmentMethod":"none","qualityTier":"silver","geoQuality":1.0,"geoRiskFlags":[],"qualityScore":0.825,"qualityPassed":true,"@context":"https://schema.org","@type":"Book","spatialCoverage":{"@type":"Place","name":"Veazie","geo":{"@type":"GeoCoordinates","longitude":-68.70531,"latitude":44.83868}},"contentLocation":{"@type":"Place","name":"Veazie","geo":{"@type":"GeoCoordinates","longitude":-68.70531,"latitude":44.83868}}}