{"id":"wd-Q6778608-Q461572","bookTitle":"Marx in Soho","author":"Howard Zinn","publishYear":1999,"placeName":"SoHo","coordinates":[-74.000833,40.723056],"placeType":"real","settingType":"primary","narrativeEra":"1999s","passage":"","sentiment":{"polarity":0.0,"dominantEmotions":[],"themes":[]},"language":"English","genres":[],"region":"North America","country":"United States","source":"wikidata","openLibraryKey":null,"wikidataBookQid":"Q6778608","wikidataPlaceQid":"Q461572","qaFlags":[],"nearestKnownCity":"New York","nearestKnownCityDistanceKm":1.22,"regionInferred":false,"placeGranularity":"city","coordinatePrecisionKm":15,"coordinateConfidence":0.85,"coordinateSource":"wikidata","geolocationNeedsReview":false,"passageSource":"wikidata","passageType":"none","enrichmentMethod":"none","qualityTier":"silver","geoQuality":1.0,"geoRiskFlags":[],"qualityScore":0.825,"qualityPassed":true,"@context":"https://schema.org","@type":"Book","spatialCoverage":{"@type":"Place","name":"SoHo","geo":{"@type":"GeoCoordinates","longitude":-74.000833,"latitude":40.723056}},"contentLocation":{"@type":"Place","name":"SoHo","geo":{"@type":"GeoCoordinates","longitude":-74.000833,"latitude":40.723056}}}