{"id":"wd-Q21855601-Q21855637","bookTitle":"Danes Are Like That!","author":"G. Prakash Reddy","publishYear":1992,"placeName":"Hvilsager","coordinates":[10.3487,56.36946],"placeType":"real","settingType":"primary","narrativeEra":"1992s","passage":"","sentiment":{"polarity":0.0,"dominantEmotions":[],"themes":[]},"language":"Danish","genres":[],"region":"Europe","country":"Denmark","source":"wikidata","openLibraryKey":null,"wikidataBookQid":"Q21855601","wikidataPlaceQid":"Q21855637","qaFlags":[],"nearestKnownCity":"Copenhagen","nearestKnownCityDistanceKm":158.01,"regionInferred":false,"placeGranularity":"city","coordinatePrecisionKm":15,"coordinateConfidence":0.85,"coordinateSource":"wikidata","geolocationNeedsReview":false,"passageSource":"wikidata","passageType":"none","enrichmentMethod":"none","qualityTier":"silver","geoQuality":1.0,"geoRiskFlags":[],"qualityScore":0.825,"qualityPassed":true,"@context":"https://schema.org","@type":"Book","spatialCoverage":{"@type":"Place","name":"Hvilsager","geo":{"@type":"GeoCoordinates","longitude":10.3487,"latitude":56.36946}},"contentLocation":{"@type":"Place","name":"Hvilsager","geo":{"@type":"GeoCoordinates","longitude":10.3487,"latitude":56.36946}}}