{"id":"wd-Q25184531-Q1788657","bookTitle":"This Sporting Life","author":"David Storey","publishYear":1960,"placeName":"Northern England","coordinates":[-2.3,55.0],"placeType":"real","settingType":"primary","narrativeEra":"1960s","passage":"","sentiment":{"polarity":0.0,"dominantEmotions":[],"themes":[]},"language":"English","genres":[],"region":"Europe","country":"United Kingdom","source":"wikidata","openLibraryKey":null,"wikidataBookQid":"Q25184531","wikidataPlaceQid":"Q1788657","qaFlags":[],"nearestKnownCity":"Edinburgh","nearestKnownCityDistanceKm":119.87,"regionInferred":false,"placeGranularity":"city","coordinatePrecisionKm":15,"coordinateConfidence":0.85,"coordinateSource":"wikidata","geolocationNeedsReview":false,"passageSource":"wikidata","passageType":"none","enrichmentMethod":"none","qualityTier":"silver","geoQuality":0.85,"geoRiskFlags":["coarse_coordinate_precision"],"qualityScore":0.78,"qualityPassed":true,"@context":"https://schema.org","@type":"Book","spatialCoverage":{"@type":"Place","name":"Northern England","geo":{"@type":"GeoCoordinates","longitude":-2.3,"latitude":55.0}},"contentLocation":{"@type":"Place","name":"Northern England","geo":{"@type":"GeoCoordinates","longitude":-2.3,"latitude":55.0}}}