{"id":"wd-Q7602538-Q39121","bookTitle":"Started Early, Took My Dog","author":"Kate Atkinson","publishYear":2010,"placeName":"Leeds","coordinates":[-1.543611111,53.7975],"placeType":"real","settingType":"primary","narrativeEra":"2010s","passage":"","sentiment":{"polarity":0.0,"dominantEmotions":[],"themes":[]},"language":"English","genres":[],"region":"Europe","country":"United Kingdom","source":"wikidata","openLibraryKey":null,"wikidataBookQid":"Q7602538","wikidataPlaceQid":"Q39121","qaFlags":[],"nearestKnownCity":"Manchester","nearestKnownCityDistanceKm":58.0,"regionInferred":false,"placeGranularity":"city","coordinatePrecisionKm":15,"coordinateConfidence":0.85,"coordinateSource":"wikidata","geolocationNeedsReview":false,"passageSource":"wikidata","passageType":"none","enrichmentMethod":"none","qualityTier":"silver","geoQuality":1.0,"geoRiskFlags":[],"qualityScore":0.825,"qualityPassed":true,"@context":"https://schema.org","@type":"Book","spatialCoverage":{"@type":"Place","name":"Leeds","geo":{"@type":"GeoCoordinates","longitude":-1.543611111,"latitude":53.7975}},"contentLocation":{"@type":"Place","name":"Leeds","geo":{"@type":"GeoCoordinates","longitude":-1.543611111,"latitude":53.7975}}}