{"id":"wd-Q10683892-Q25287","bookTitle":"Sunes tusen tjusarknep","author":"Anders Jacobsson","publishYear":2008,"placeName":"Gothenburg","coordinates":[11.9675,57.7075],"placeType":"real","settingType":"primary","narrativeEra":"2008s","passage":"","sentiment":{"polarity":0.6,"dominantEmotions":["mischief","playfulness","restlessness"],"themes":["suburban_adolescent_yearning","social_embarrassment","middle_class_family_dynamics","first_love_pursuits","gothenburg_urban_mobility"]},"language":"Swedish","genres":[],"region":"Europe","country":"Sweden","source":"wikidata","openLibraryKey":null,"wikidataBookQid":"Q10683892","wikidataPlaceQid":"Q25287","qaFlags":["far_from_known_city"],"nearestKnownCity":"London","nearestKnownCityDistanceKm":1037.52,"regionInferred":true,"literaryMood":"humorous_adolescent_realism","placeGranularity":"city","coordinatePrecisionKm":15,"coordinateConfidence":0.85,"coordinateSource":"wikidata","geolocationNeedsReview":false,"passageSource":"wikidata","passageType":"none","enrichmentMethod":"gemini_reputation","qualityTier":"silver","geoQuality":1.0,"geoRiskFlags":[],"qualityScore":0.825,"qualityPassed":true,"@context":"https://schema.org","@type":"Book","spatialCoverage":{"@type":"Place","name":"Gothenburg","geo":{"@type":"GeoCoordinates","longitude":11.9675,"latitude":57.7075}},"contentLocation":{"@type":"Place","name":"Gothenburg","geo":{"@type":"GeoCoordinates","longitude":11.9675,"latitude":57.7075}}}