{"id":"cif-168-mumbai","bookTitle":"The House of Nothing","author":"Guruguhan Iyer","publishYear":2025,"placeName":"Mumbai","coordinates":[72.8777,19.076],"placeType":"real","settingType":"primary","narrativeEra":"2025s","passage":"\"Shunya Vedana … Shunya Vedana … Shunya Vedana …\". The chanting never stops at 7, Srujan Nivas. It looks like an ordinary flat, but is it? Ramana and Meenakshi move into their new home right after their wedding. Three days later, his parents visit them, drift off under the ceiling fan, and die in their sleep. Two decades later, Meenakshi meets the same fate. Their son Venkat realises his family's living the last phase of their lives over and over. Shunya and Vedana, the self-proclaimed Gods, promise liberation in exchange for Venkat's complete surrender. Will he yield or is there something far bigger at play? The story is set in Matunga, Mumbai. The restaurants, shops and temples mentioned are real.","sentiment":{"polarity":-0.6,"dominantEmotions":["claustrophobia","eeriness","paranoia","suffocation","helplessness"],"themes":["intergenerational_trauma","domestic_occultism","urban_confinement","cycle_of_fatality","theological_coercion","matunga_traditionalism"]},"language":"English","genres":["literary fiction"],"region":"South Asia","source":"citiesinfiction","goodreadsUrl":"https://books.google.com/books?q=The%20House%20of%20Nothing%20Guruguhan%20Iyer","literaryMood":"gothic-suburban","placeGranularity":"city","coordinatePrecisionKm":15,"coordinateConfidence":0.85,"coordinateSource":"citiesinfiction","geolocationNeedsReview":false,"passageSource":"citiesinfiction","passageType":"literary_excerpt","enrichmentMethod":"gemini_passage","qualityTier":"gold","geoQuality":1.0,"geoRiskFlags":[],"qualityScore":1.0,"qualityPassed":true,"@context":"https://schema.org","@type":"Book","spatialCoverage":{"@type":"Place","name":"Mumbai","geo":{"@type":"GeoCoordinates","longitude":72.8777,"latitude":19.076}},"contentLocation":{"@type":"Place","name":"Mumbai","geo":{"@type":"GeoCoordinates","longitude":72.8777,"latitude":19.076}}}