{"id":"cif-kintsugi","bookTitle":"Kintsugi","author":"Anukrti Upadhyay","publishYear":2020,"placeName":"Jaipur","coordinates":[75.7873,26.9124],"placeType":"real","settingType":"primary","narrativeEra":"2020s","passage":"","sentiment":{"polarity":0.2,"dominantEmotions":["bittersweet","restlessness","tenderness","languor"],"themes":["gendered_identity","traditional_craftsmanship","transnational_displacement","intergenerational_trauma","curated_aesthetics"]},"language":"English","genres":["literary fiction"],"region":"South Asia","goodreadsUrl":"https://books.google.com/books?q=Kintsugi%20Anukrti%20Upadhyay","literaryMood":"meditative","placeGranularity":"city","coordinatePrecisionKm":15,"coordinateConfidence":0.85,"coordinateSource":"dataset","geolocationNeedsReview":false,"passageSource":"unknown","passageType":"none","enrichmentMethod":"gemini_reputation","qualityTier":"silver","geoQuality":1.0,"geoRiskFlags":[],"qualityScore":0.825,"qualityPassed":true,"@context":"https://schema.org","@type":"Book","spatialCoverage":{"@type":"Place","name":"Jaipur","geo":{"@type":"GeoCoordinates","longitude":75.7873,"latitude":26.9124}},"contentLocation":{"@type":"Place","name":"Jaipur","geo":{"@type":"GeoCoordinates","longitude":75.7873,"latitude":26.9124}}}