{"id":"cif-jump-cut","bookTitle":"Jump Cut","author":"Krishna Shastri Devulapalli","publishYear":2013,"placeName":"Chennai","coordinates":[80.2707,13.0827],"placeType":"real","settingType":"primary","narrativeEra":"2013s","passage":"","sentiment":{"polarity":0.4,"dominantEmotions":["mischief","playfulness","restlessness","intoxication"],"themes":["film_industry_satire","urban_media_culture","middle_class_absurdity","cinephilia","bureaucratic_farcicality"]},"language":"English","genres":["literary fiction"],"region":"South Asia","goodreadsUrl":"https://books.google.com/books?q=Jump%20Cut%20Krishna%20Shastri%20Devulapalli","literaryMood":"irreverent","placeGranularity":"city","coordinatePrecisionKm":15,"coordinateConfidence":0.85,"coordinateSource":"dataset","geolocationNeedsReview":false,"passageSource":"unknown","passageType":"none","enrichmentMethod":"gemini_reputation","qualityTier":"silver","geoQuality":1.0,"geoRiskFlags":[],"qualityScore":0.825,"qualityPassed":true,"@context":"https://schema.org","@type":"Book","spatialCoverage":{"@type":"Place","name":"Chennai","geo":{"@type":"GeoCoordinates","longitude":80.2707,"latitude":13.0827}},"contentLocation":{"@type":"Place","name":"Chennai","geo":{"@type":"GeoCoordinates","longitude":80.2707,"latitude":13.0827}}}