{"id":"cif-55-ranaghat","bookTitle":"Adarsha Hindu Hotel","author":"Bibhutibhushan Bandopadhyay","publishYear":1940,"placeName":"Ranaghat","coordinates":[88.57,23.18],"placeType":"real","settingType":"primary","narrativeEra":"1940s","passage":"A novel about a pice hotel during WWII in Bengal, about its owner/chef, maid, suppliers and how their lives are intertwined together. this is a rare culinary fiction in Bangla. A film and a tv serial were made based on the novel in 1957 and 1989 respectively. Trivia: the author also wrote 'Pather Panchali' and Satyajit Ray made a film based on it.","sentiment":{"polarity":0.2,"dominantEmotions":["hunger","pride","wistfulness","solidarity","languor"],"themes":["culinary_craftsmanship","wartime_scarcity","rural_urban_migration","dignity_of_labor","pice_hotel_economics","transient_human_connections"]},"language":"Bengali","genres":["literary fiction"],"region":"South Asia","source":"citiesinfiction","goodreadsUrl":"https://books.google.com/books?q=Adarsha%20Hindu%20Hotel%20Bibhutibhushan%20Bandopadhyay","literaryMood":"evocative","placeGranularity":"city","coordinatePrecisionKm":15,"coordinateConfidence":0.85,"coordinateSource":"citiesinfiction","geolocationNeedsReview":false,"passageSource":"citiesinfiction","passageType":"other","enrichmentMethod":"gemini_passage","qualityTier":"gold","geoQuality":1.0,"geoRiskFlags":[],"qualityScore":1.0,"qualityPassed":true,"@context":"https://schema.org","@type":"Book","spatialCoverage":{"@type":"Place","name":"Ranaghat","geo":{"@type":"GeoCoordinates","longitude":88.57,"latitude":23.18}},"contentLocation":{"@type":"Place","name":"Ranaghat","geo":{"@type":"GeoCoordinates","longitude":88.57,"latitude":23.18}}}