{"id":"cif-173-shillong","bookTitle":"We come from the Mist: Writings from the Meghalaya","author":"Edited by Janice Pariat","publishYear":2023,"placeName":"Shillong","coordinates":[91.8933,25.5788],"placeType":"real","settingType":"primary","narrativeEra":"2023s","passage":"","sentiment":{"polarity":0.6,"dominantEmotions":["reverence","wistfulness","solidarity","serenity"],"themes":["indigenous_cosmology","ecocriticism","oral_tradition_preservation","postcolonial_identity","mythic_geography","khasi_matrilineal_heritage"]},"language":"English","genres":["anthology"],"region":"South Asia","source":"citiesinfiction","goodreadsUrl":"https://books.google.com/books?q=We%20come%20from%20the%20Mist%3A%20Writings%20from%20the%20Meghalaya%20Edited%20by%20Janice%20Pariat","literaryMood":"evocative","placeGranularity":"city","coordinatePrecisionKm":15,"coordinateConfidence":0.85,"coordinateSource":"citiesinfiction","geolocationNeedsReview":false,"passageSource":"citiesinfiction","passageType":"none","enrichmentMethod":"gemini_reputation","qualityTier":"silver","geoQuality":1.0,"geoRiskFlags":[],"qualityScore":0.825,"qualityPassed":true,"@context":"https://schema.org","@type":"Book","spatialCoverage":{"@type":"Place","name":"Shillong","geo":{"@type":"GeoCoordinates","longitude":91.8933,"latitude":25.5788}},"contentLocation":{"@type":"Place","name":"Shillong","geo":{"@type":"GeoCoordinates","longitude":91.8933,"latitude":25.5788}}}