{"id":"cif-long-night-of-storm","bookTitle":"Long Night of Storm","author":"Indrabhadur Rai","publishYear":2018,"placeName":"Darjeeling","coordinates":[88.2631,27.036],"placeType":"real","settingType":"primary","narrativeEra":"2018s","passage":"","sentiment":{"polarity":-0.4,"dominantEmotions":["wistfulness","claustrophobia","fever","helplessness"],"themes":["gorkhaland_agitation","ethnic_alienation","post_colonial_limbo","political_stagnation","mountain_isolation","displacement_of_identity"]},"language":"Nepali","genres":["short stories"],"region":"South Asia","goodreadsUrl":"https://books.google.com/books?q=Long%20Night%20of%20Storm%20Indrabhadur%20Rai","literaryMood":"melancholic_realism","placeGranularity":"city","coordinatePrecisionKm":15,"coordinateConfidence":0.85,"coordinateSource":"dataset","geolocationNeedsReview":false,"passageSource":"unknown","passageType":"none","enrichmentMethod":"gemini_reputation","qualityTier":"silver","geoQuality":1.0,"geoRiskFlags":[],"qualityScore":0.825,"qualityPassed":true,"@context":"https://schema.org","@type":"Book","spatialCoverage":{"@type":"Place","name":"Darjeeling","geo":{"@type":"GeoCoordinates","longitude":88.2631,"latitude":27.036}},"contentLocation":{"@type":"Place","name":"Darjeeling","geo":{"@type":"GeoCoordinates","longitude":88.2631,"latitude":27.036}}}