{"id":"cif-the-tamarind-tree","bookTitle":"The Tamarind Tree","author":"Sundara Ramaswamy","publishYear":2022,"placeName":"Nagercoil","coordinates":[77.4119,8.1833],"placeType":"real","settingType":"primary","narrativeEra":"2022s","passage":"","sentiment":{"polarity":0.4,"dominantEmotions":["wistfulness","serenity","reverence","restlessness"],"themes":["intergenerational_memory","urban_modernization","agrarian_disappearance","communal_stasis","ephemeral_tradition"]},"language":"English","genres":["literary fiction"],"region":"South Asia","goodreadsUrl":"https://books.google.com/books?q=The%20Tamarind%20Tree%20Sundara%20Ramaswamy","literaryMood":"meditative","placeGranularity":"city","coordinatePrecisionKm":15,"coordinateConfidence":0.85,"coordinateSource":"dataset","geolocationNeedsReview":false,"passageSource":"unknown","passageType":"none","enrichmentMethod":"gemini_reputation","qualityTier":"silver","geoQuality":1.0,"geoRiskFlags":[],"qualityScore":0.825,"qualityPassed":true,"@context":"https://schema.org","@type":"Book","spatialCoverage":{"@type":"Place","name":"Nagercoil","geo":{"@type":"GeoCoordinates","longitude":77.4119,"latitude":8.1833}},"contentLocation":{"@type":"Place","name":"Nagercoil","geo":{"@type":"GeoCoordinates","longitude":77.4119,"latitude":8.1833}}}